apistar_token_auth/__init__.py
apistar_token_auth/authentication.py
apistar_token_auth/compat.py
apistar_token_auth/handlers.py
apistar_token_auth/schemas.py
apistar_token_auth/settings.py
apistar_token_auth/utils.py
apistar_token_auth-1.1.dist-info/DESCRIPTION.rst
apistar_token_auth-1.1.dist-info/METADATA
apistar_token_auth-1.1.dist-info/RECORD
apistar_token_auth-1.1.dist-info/WHEEL
apistar_token_auth-1.1.dist-info/metadata.json
apistar_token_auth-1.1.dist-info/top_level.txt
