Metadata-Version: 2.0
Name: apistar-token-auth
Version: 1.1
Summary: Token Based Authentication for API Star
Home-page: https://github.com/bahattincinic/apistar_token_authentication
Author: Bahattin Cinic
Author-email: bahattincinic@gmail.com
License: MIT
Platform: UNKNOWN
Classifier: Environment :: Web Environment
Classifier: Intended Audience :: Developers
Classifier: Programming Language :: Python
Classifier: Programming Language :: Python :: 3
Classifier: Topic :: Internet :: WWW/HTTP
Requires-Dist: apistar
